[{"s": "pult-dlya-magnitoly-teyes-cc3", "t": "Пульт для магнитолы Teyes CC3: управление, настройка и альтернативы", "i": "📁", "c": "drugoe"}, {"s": "puma-tyazhelyj-bronetransporter", "t": "Пума: тяжелый бронетранспортер — ТТХ, особенности, сравнение с аналогами", "i": "📁", "c": "drugoe"}, {"s": "puteshestvie-po-polotsku", "t": "Путешествие по Полоцку: маршруты, достопримечательности и советы туристам", "i": "📁", "c": "drugoe"}, {"s": "pult-dlya-teyes-cc3-2k", "t": "Пульт для Teyes CC3 2K: выбор, настройка и ремонт (2026)", "i": "📁", "c": "drugoe"}, {"s": "putorana-gde-raspolozhen", "t": "Путорана: где находится плато, как добраться и что посмотреть", "i": "📁", "c": "drugoe"}, {"s": "pugv-i-vvg-otlichie", "t": "ПУГВ и ВВГ: ключевые отличия кабелей для электропроводки", "i": "📁", "c": "drugoe"}, {"s": "pugvv-ili-pvs-v-chem-raznitsa", "t": "ПУГВВ или ПВС: в чем разница и что выбрать для проводки?", "i": "📁", "c": "drugoe"}, {"s": "pugnp-ili-shvvp", "t": "ПУГНП или ШВВП: что лучше для проводки в доме и машине в 2026 году?", "i": "📁", "c": "drugoe"}, {"s": "pugvv-i-shvvp-otlichiya", "t": "ПУГВВ и ШВВП: ключевые отличия, применение и выбор кабеля", "i": "📁", "c": "drugoe"}, {"s": "pult-dlya-magnitoly-teyes-cc3l", "t": "Пульт для магнитолы Teyes CC3L: выбор, настройка и ремонт", "i": "📁", "c": "tiguan"}, {"s": "pugv-i-pugvv-v-chem-raznitsa", "t": "ПУГВ и ПУГВВ: в чем разница и что выбрать для проводки", "i": "📁", "c": "drugoe"}, {"s": "punkt-pdd-vyezd-na-polosu-vstrechnogo-dvizheniya", "t": "Выезд на встречную полосу: штрафы ПДД 2026 и как избежать лишения прав", "i": "📁", "c": "drugoe"}]